Workbook

Sheet Seguridad Social
A1: salario minimo
A2: EMPLEADO | B2: CEDULA | C2: NOMBRES | D2: TIPO DE SALARI | E2: DIAS LABORADOS MES | F2: DIAS VAC/LICENCIAS | G2: DIAS INCAPACIDAD | H2: INGRESOS SALARIALES | I2: IBC INICIAL | J2: INGRESOS NO SALARIALES | K2: TOTAL INGRESOS | L2: 40% INGRESOS | M2: EXCESO | N2: 0.7 | O2: IBC 1393 | P2: IBC MES ANTERIOR | Q2: IBC VACACIONES | R2: IBC INCAPACIDADES/LICENCIAS | S2: TOTAL IBC MES SEGURIDAD SOCIAL | T2: PENSIONADO | U2: APORTE SALUD | V2: APORTE SALUD SISTEMA | W2: DIFERENCIA | X2: APORTE PENSION | Y2: APORTE PENSION SISTEMA | Z2: DIFERENCIA | AA2: TOTAL IBC MES FONDO | AB2: APORTE FONDO | AC2: APORTE FONDO SISTEMA | AD2: DIFERENCIA | AF2: nuevo salario | AG2: IBC ACTUAL | AH2: IBC MES ANTERIOR | AJ2: fs empleador | AK2: OBSERVACIONES
A3: 20031311 | B3: 46377202 | C3: RODRIGUEZ CRUZ EDITH JULIETA | D3: Integral | E3: 31 | F3: 1 | G3: 0 | H3: 30725865 | I3: 21508106 | J3: 921700 | K3: 31647565 | L3: 12659026 | P3: 18468313 | Q3: 615610 | R3: 0 | V3: 884948 | Y3: 884948 | AC3: 221400 | AF3: =VLOOKUP(A3,Devengos!$A$4:$I$389,9,0) -> 22761766 | AG3: =IF(D3="Integral",ROUND(AF3*70%,0),AF3) -> 15933236 | AH3: =IFERROR(VLOOKUP(B3,'Planilla Mes anterior'!$CX:$CY,2,0),0) -> 18468313 | AJ3: 0
A4: 20032632 | B4: 1.0208468e+09 | C4: AVELLO ALVAREZ JUAN JOSE | D4: Integral | E4: 30 | F4: 0 | G4: 0 | H4: 22761765 | I4: 15933235 | J4: 859700 | K4: 23621465 | L4: 9448586 | P4: 15933236 | Q4: 0 | R4: 0 | V4: 637329 | Y4: 637329 | AC4: 159400 | AF4: =VLOOKUP(A4,Devengos!$A$4:$I$389,9,0) -> 22761765 | AG4: =IF(D4="Integral",ROUND(AF4*70%,0),AF4) -> 15933236 | AH4: =IFERROR(VLOOKUP(B4,'Planilla Mes anterior'!$CX:$CY,2,0),0) -> 15933236 | AJ4: 0
A5: 20032638 | B5: 94416294 | C5: VALDERRAMA CONCHA ANDRES FELIPE | D5: Integral | E5: 31 | F5: 0 | G5: 0 | H5: 42589681 | I5: 29812777 | J5: 2288938 | K5: 44878619 | L5: 17951448 | P5: 28800088 | Q5: 0 | R5: 0 | V5: 1192511 | Y5: 1192511 | AC5: 417500 | AF5: =VLOOKUP(A5,Devengos!$A$4:$I$389,9,0) -> 33602815 | AG5: =IF(D5="Integral",ROUND(AF5*70%,0),AF5) -> 23521971 | AH5: =IFERROR(VLOOKUP(B5,'Planilla Mes anterior'!$CX:$CY,2,0),0) -> 28800088 | AJ5: 0
A6: 20032640 | B6: 51813374 | C6: SANCHEZ TEJADA ADRIANA | D6: Integral | E6: 31 | F6: 0 | G6: 0 | H6: 33430177 | I6: 23401124 | J6: 1065836 | K6: 34496013 | L6: 13798405 | P6: 19218024 | Q6: 0 | R6: 0 | V6: 936045 | Y6: 0 | AB6: 0 | AC6: 0 | AD6: 0 | AF6: =VLOOKUP(A6,Devengos!$A$4:$I$389,9,0) -> 22819376 | AG6: =IF(D6="Integral",ROUND(AF6*70%,0),AF6) -> 15973563 | AH6: =IFERROR(VLOOKUP(B6,'Planilla Mes anterior'!$CX:$CY,2,0),0) -> 19218024 | AJ6: 0
A7: 20032652 | B7: 98624466 | C7: GARCIA LEON EDISSON AUGUSTO | D7: Normal | E7: 30 | F7: 0 | G7: 2 | H7: 11096741 | I7: 11096741 | J7: 811300 | K7: 11908041 | L7: 4763216 | P7: 11096741 | Q7: 0 | R7: 0 | T7: 0 | V7: 443869 | Y7: 443869 | AC7: 111000 | AF7: =VLOOKUP(A7,Devengos!$A$4:$I$389,9,0) -> 11096741 | AG7: =IF(D7="Integral",ROUND(AF7*70%,0),AF7) -> 11096741 | AH7: =IFERROR(VLOOKUP(B7,'Planilla Mes anterior'!$CX:$CY,2,0),0) -> 11096741 | AJ7: 0
A8: 20039921 | B8: 79864894 | C8: MOLINA JUNCO HUGO ALEXANDER | D8: Normal | E8: 30 | F8: 0 | G8: 0 | H8: 12941846 | I8: 12941846 | J8: 829900 | K8: 13771746 | L8: 5508698 | P8: 12941846 | Q8: 0 | R8: 0 | T8: 0 | V8: 517674 | Y8: 517674 | AC8: 129600 | AF8: =VLOOKUP(A8,Devengos!$A$4:$I$389,9,0) -> 12941846 | AG8: =IF(D8="Integral",ROUND(AF8*70%,0),AF8) -> 12941846 | AH8: =IFERROR(VLOOKUP(B8,'Planilla Mes anterior'!$CX:$CY,2,0),0) -> 12941846 | AJ8: 0
A9: 20042066 | B9: 94469034 | C9: BRAVO SOLARTE HECTOR MARIO | D9: Integral | E9: 42 | F9: 0 | G9: 11 | H9: 32559810 | I9: 22791867 | J9: 931900 | K9: 33491710 | L9: 13396684 | P9: 24539605 | Q9: 0 | R9: 0 | S9: 23129377 | U9: 925175.06 | V9: 925175 | W9: 0.064 | Y9: 925175 | AC9: 231600 | AF9: =VLOOKUP(A9,Devengos!$A$4:$I$389,9,0) -> 30673334 | AG9: =IF(D9="Integral",ROUND(AF9*70%,0),AF9) -> 21471334 | AH9: =IFERROR(VLOOKUP(B9,'Planilla Mes anterior'!$CX:$CY,2,0),0) -> 24539605 | AJ9: 0 | AK9: TOMA SALARIO * 70%+ LOS SALARIALES AL 70% Y EL PAGO DEL 100% DE LA INCAPACIDAD INCLUIDO EL AUXILIO ASUMIDO
A10: 20047370 | B10: 1127577184 | C10: MEZA PAUL MARIA ALEJANDRA | D10: Integral | E10: 31 | F10: 0 | G10: 0 | H10: 29773237 | I10: 20841266 | J10: 1108900 | K10: 30882137 | L10: 12352855 | P10: 18666001 | Q10: 0 | R10: 0 | V10: 833651 | Y10: 833651 | AC10: 208600 | AF10: =VLOOKUP(A10,Devengos!$A$4:$I$389,9,0) -> 23832382 | AG10: =IF(D10="Integral",ROUND(AF10*70%,0),AF10) -> 16682667 | AH10: =IFERROR(VLOOKUP(B10,'Planilla Mes anterior'!$CX:$CY,2,0),0) -> 18666001 | AJ10: 0
A11: 20049357 | B11: 424785 | C11: SEGURA FRANCOIS ALBERT | D11: Integral | E11: 31 | F11: 0 | G11: 0 | H11: 27738862 | I11: 19417203 | J11: 894500 | K11: 28633362 | L11: 11453345 | P11: 17675220 | Q11: 0 | R11: 0 | V11: 776688 | Y11: 776688 | AC11: 194200 | AF11: =VLOOKUP(A11,Devengos!$A$4:$I$389,9,0) -> 22761766 | AG11: =IF(D11="Integral",ROUND(AF11*70%,0),AF11) -> 15933236 | AH11: =IFERROR(VLOOKUP(B11,'Planilla Mes anterior'!$CX:$CY,2,0),0) -> 17675220 | AJ11: 0
A12: 20059280 | B12: 71269226 | C12: RUIZ MARTINEZ JUAN CAMILO | D12: Integral | E12: 30 | F12: 1 | G12: 0 | H12: 24203344 | I12: 16942341 | J12: 875300 | K12: 25078644 | L12: 10031458 | P12: 15933236 | Q12: 531108 | R12: 0 | V12: 698938 | Y12: 698938 | AC12: 175000 | AF12: =VLOOKUP(A12,Devengos!$A$4:$I$389,9,0) -> 25037942 | AG12: =IF(D12="Integral",ROUND(AF12*70%,0),AF12) -> 17526559 | AH12: =IFERROR(VLOOKUP(B12,'Planilla Mes anterior'!$CX:$CY,2,0),0) -> 15933236 | AJ12: 0
A13: 20060771 | B13: 1.0184065e+09 | C13: RICO HERNANDEZ OSCAR EDUARDO | D13: Normal | E13: 30 | F13: 2 | G13: 0 | H13: 13952910 | I13: 13952910 | J13: 869100 | K13: 14822010 | L13: 5928804 | P13: 43772625 | Q13: 2918175 | R13: 0 | T13: 0 | V13: 674843 | Y13: 674843 | AC13: 168800 | AF13: =VLOOKUP(A13,Devengos!$A$4:$I$389,9,0) -> 14949546 | AG13: =IF(D13="Integral",ROUND(AF13*70%,0),AF13) -> 14949546 | AH13: =IFERROR(VLOOKUP(B13,'Planilla Mes anterior'!$CX:$CY,2,0),0) -> 43772625 | AJ13: 0
A14: 20060845 | B14: 1018406436 | C14: RODRIGUEZ MOLINA JOSE DAVID | D14: Integral | E14: 30 | F14: 0 | G14: 0 | H14: 22761765 | I14: 15933235 | J14: 859700 | K14: 23621465 | L14: 9448586 | P14: 15955734 | Q14: 0 | R14: 0 | V14: 637329 | Y14: 637329 | AC14: 159400 | AF14: =VLOOKUP(A14,Devengos!$A$4:$I$389,9,0) -> 22761765 | AG14: =IF(D14="Integral",ROUND(AF14*70%,0),AF14) -> 15933236 | AH14: =IFERROR(VLOOKUP(B14,'Planilla Mes anterior'!$CX:$CY,2,0),0) -> 15955734 | AJ14: 0
A15: 20065526 | B15: 52530451 | C15: PEÑA CARDENAS ERIKA YOLIMA | D15: Normal | E15: 30 | F15: 0 | G15: 0 | H15: 9525854 | I15: 9525854 | J15: 795700 | K15: 10321554 | L15: 4128622 | P15: 9525854 | Q15: 0 | R15: 0 | T15: 0 | V15: 381034 | Y15: 381034 | AC15: 95400 | AF15: =VLOOKUP(A15,Devengos!$A$4:$I$389,9,0) -> 9525854 | AG15: =IF(D15="Integral",ROUND(AF15*70%,0),AF15) -> 9525854 | AH15: =IFERROR(VLOOKUP(B15,'Planilla Mes anterior'!$CX:$CY,2,0),0) -> 9525854 | AJ15: 0
A16: 20066234 | B16: 502210 | C16: TACORONTE RIVERO ERNESTO LUIS | D16: Integral | E16: 30 | F16: 0 | G16: 0 | H16: 28483101 | I16: 19938171 | J16: 899700 | K16: 29382801 | L16: 11753120 | P16: 19938171 | Q16: 0 | R16: 0 | V16: 797527 | Y16: 797527 | AC16: 199400 | AF16: =VLOOKUP(A16,Devengos!$A$4:$I$389,9,0) -> 28483101 | AG16: =IF(D16="Integral",ROUND(AF16*70%,0),AF16) -> 19938171 | AH16: =IFERROR(VLOOKUP(B16,'Planilla Mes anterior'!$CX:$CY,2,0),0) -> 19938171 | AJ16: 0
A17: 20066799 | B17: 1020796094 | C17: ALBESANO RODRIGUEZ TOMAS ENRICO | D17: Normal | E17: 31 | F17: 0 | G17: 0 | H17: 12834012 | I17: 12834012 | J17: 2525372 | K17: 15359384 | L17: 6143754 | P17: 13976000 | Q17: 0 | R17: 0 | T17: 0 | V17: 513360 | Y17: 513360 | AC17: 128400 | AF17: =VLOOKUP(A17,Devengos!$A$4:$I$389,9,0) -> 12525864 | AG17: =IF(D17="Integral",ROUND(AF17*70%,0),AF17) -> 12525864 | AH17: =IFERROR(VLOOKUP(B17,'Planilla Mes anterior'!$CX:$CY,2,0),0) -> 13976000 | AJ17: 0
A18: 20066836 | B18: 72266298 | C18: ZARATE LOPEZ MARCO TULIO | D18: Normal | E18: 31 | F18: 1 | G18: 0 | H18: 27218173 | I18: 27218173 | J18: 1243949 | K18: 28462122 | L18: 11384849 | P18: 24946729 | Q18: 831558 | R18: 0 | T18: 0 | V18: 1121989 | Y18: 1121989 | AC18: 336800 | AF18: =VLOOKUP(A18,Devengos!$A$4:$I$389,9,0) -> 22761765 | AG18: =IF(D18="Integral",ROUND(AF18*70%,0),AF18) -> 22761765 | AH18: =IFERROR(VLOOKUP(B18,'Planilla Mes anterior'!$CX:$CY,2,0),0) -> 24946729 | AJ18: 0
A19: 20068049 | B19: 1014191248 | C19: CALDERON MANCHEGO JOSE ERNESTO | D19: Normal | E19: 30 | F19: 0 | G19: 0 | H19: 8956566 | I19: 8956566 | J19: 789900 | K19: 9746466 | L19: 3898586 | P19: 8956566 | Q19: 0 | R19: 0 | T19: 0 | V19: 358263 | Y19: 358263 | AC19: 89600 | AF19: =VLOOKUP(A19,Devengos!$A$4:$I$389,9,0) -> 8956566 | AG19: =IF(D19="Integral",ROUND(AF19*70%,0),AF19) -> 8956566 | AH19: =IFERROR(VLOOKUP(B19,'Planilla Mes anterior'!$CX:$CY,2,0),0) -> 8956566 | AJ19: 0
A20: 20068059 | B20: 79521449 | C20: RAMIREZ RODRIGUEZ JUVENAL HUMBERTO | D20: Normal | E20: 30 | F20: 0 | G20: 0 | H20: 13325016 | I20: 13325016 | J20: 1637817 | K20: 14962833 | L20: 5985133 | P20: 14162837 | Q20: 0 | R20: 0 | T20: 0 | V20: 533001 | Y20: 533001 | AC20: 133400 | AF20: =VLOOKUP(A20,Devengos!$A$4:$I$389,9,0) -> 13325016 | AG20: =IF(D20="Integral",ROUND(AF20*70%,0),AF20) -> 13325016 | AH20: =IFERROR(VLOOKUP(B20,'Planilla Mes anterior'!$CX:$CY,2,0),0) -> 14162837 | AJ20: 0
A21: 20069425 | B21: 88233100 | C21: LIZCANO GOMEZ RICARDO | D21: Integral | E21: 30 | F21: 0 | G21: 0 | H21: 22761765 | I21: 15933235 | J21: 859700 | K21: 23621465 | L21: 9448586 | P21: 15933236 | Q21: 0 | R21: 0 | V21: 637329 | Y21: 637329 | AC21: 159400 | AF21: =VLOOKUP(A21,Devengos!$A$4:$I$389,9,0) -> 22761765 | AG21: =IF(D21="Integral",ROUND(AF21*70%,0),AF21) -> 15933236 | AH21: =IFERROR(VLOOKUP(B21,'Planilla Mes anterior'!$CX:$CY,2,0),0) -> 15933236 | AJ21: 0
A22: 20073842 | B22: 16928777 | C22: GOMEZ SANTOFIMIO NESTOR JAVIER | D22: Integral | E22: 30 | F22: 0 | G22: 0 | H22: 27360609 | I22: 19152426 | J22: 891900 | K22: 28252509 | L22: 11301004 | P22: 19152427 | Q22: 0 | R22: 0 | V22: 766097 | Y22: 766097 | AC22: 191600 | AF22: =VLOOKUP(A22,Devengos!$A$4:$I$389,9,0) -> 27360609 | AG22: =IF(D22="Integral",ROUND(AF22*70%,0),AF22) -> 19152426 | AH22: =IFERROR(VLOOKUP(B22,'Planilla Mes anterior'!$CX:$CY,2,0),0) -> 19152427 | AJ22: 0
A23: 20075245 | B23: 1144151741 | C23: RESTREPO MARIN PAOLA | D23: Normal | E23: 30 | F23: 0 | G23: 0 | H23: 7411661 | I23: 7411661 | J23: 975529 | K23: 8387190 | L23: 3354876 | P23: 7411661 | Q23: 0 | R23: 0 | T23: 0 | V23: 296466 | Y23: 296466 | AC23: 74200 | AF23: =VLOOKUP(A23,Devengos!$A$4:$I$389,9,0) -> 7411661 | AG23: =IF(D23="Integral",ROUND(AF23*70%,0),AF23) -> 7411661 | AH23: =IFERROR(VLOOKUP(B23,'Planilla Mes anterior'!$CX:$CY,2,0),0) -> 7411661 | AJ23: 0
A24: 20075298 | B24: 1032380630 | C24: POLO TORRES SORAIMA SELENE | D24: Normal | E24: 30 | F24: 10 | G24: 0 | H24: 8311974 | I24: 8311974 | J24: 825100 | K24: 9137074 | L24: 3654830 | P24: 12467961 | Q24: 4155987 | R24: 0 | T24: 0 | V24: 498719 | Y24: 498719 | AC24: 124800 | AF24: =VLOOKUP(A24,Devengos!$A$4:$I$389,9,0) -> 12467961 | AG24: =IF(D24="Integral",ROUND(AF24*70%,0),AF24) -> 12467961 | AH24: =IFERROR(VLOOKUP(B24,'Planilla Mes anterior'!$CX:$CY,2,0),0) -> 12467961 | AJ24: 0
A25: 20075317 | B25: 94552091 | C25: VELASCO BURBANO GUSTAVO ADOLFO | D25: Normal | E25: 30 | F25: 0 | G25: 0 | H25: 8920122 | I25: 8920122 | J25: 789700 | K25: 9709822 | L25: 3883929 | P25: 9411060 | Q25: 0 | R25: 0 | T25: 0 | V25: 356805 | Y25: 356805 | AC25: 89400 | AF25: =VLOOKUP(A25,Devengos!$A$4:$I$389,9,0) -> 8324189 | AG25: =IF(D25="Integral",ROUND(AF25*70%,0),AF25) -> 8324189 | AH25: =IFERROR(VLOOKUP(B25,'Planilla Mes anterior'!$CX:$CY,2,0),0) -> 9411060 | AJ25: 0
A26: 20077129 | B26: 38565334 | C26: CALDERON QUEVEDO EVELIN ELISA | D26: Integral | E26: 31 | F26: 0 | G26: 0 | H26: 29343117 | I26: 20540182 | J26: 905900 | K26: 30249017 | L26: 12099607 | P26: 15933237 | Q26: 0 | R26: 0 | V26: 821607 | Y26: 821607 | AC26: 205600 | AF26: =VLOOKUP(A26,Devengos!$A$4:$I$389,9,0) -> 22761766 | AG26: =IF(D26="Integral",ROUND(AF26*70%,0),AF26) -> 15933236 | AH26: =IFERROR(VLOOKUP(B26,'Planilla Mes anterior'!$CX:$CY,2,0),0) -> 15933237 | AJ26: 0
A27: 20080480 | B27: 1.0207461e+09 | C27: MITROSBARAS VARGAS COSTANTINO | D27: Integral | E27: 31 | F27: 0 | G27: 0 | H27: 28470583 | I27: 19929408 | J27: 899700 | K27: 29370283 | L27: 11748113 | P27: 20889137 | Q27: 0 | R27: 0 | V27: 797176 | Y27: 797176 | AC27: 199400 | AF27: =VLOOKUP(A27,Devengos!$A$4:$I$389,9,0) -> 22761766 | AG27: =IF(D27="Integral",ROUND(AF27*70%,0),AF27) -> 15933236 | AH27: =IFERROR(VLOOKUP(B27,'Planilla Mes anterior'!$CX:$CY,2,0),0) -> 20889137 | AJ27: 0
A28: 20081518 | B28: 7183581 | C28: BLANCO LEGUIZAMON DIEGO RICARDO | D28: Integral | E28: 30 | F28: 0 | G28: 0 | H28: 22761766 | I28: 15933236 | J28: 1362295 | K28: 24124061 | L28: 9649624 | P28: 27123777 | Q28: 0 | R28: 0 | V28: 637329 | Y28: 637329 | AC28: 159400 | AF28: =VLOOKUP(A28,Devengos!$A$4:$I$389,9,0) -> 22761766 | AG28: =IF(D28="Integral",ROUND(AF28*70%,0),AF28) -> 15933236 | AH28: =IFERROR(VLOOKUP(B28,'Planilla Mes anterior'!$CX:$CY,2,0),0) -> 18986644 | AJ28: 0 | AK28: TOMA SALARIO * 70%+ LOS SALARIALES AL 70% Y EL PAGO DEL 100% DE LA INCAPACIDAD INCLUIDO EL AUXILIO ASUMIDO
A29: 20087553 | B29: 11233975 | C29: BELTRAN RODRIGUEZ EDICSON ARNETH | D29: Normal | E29: 30 | F29: 0 | G29: 0 | H29: 5628456 | I29: 5628456 | J29: 700300 | K29: 6328756 | L29: 2531502 | P29: 5628456 | Q29: 0 | R29: 0 | T29: 0 | V29: 225138 | Y29: 225138 | AC29: 0 | AF29: =VLOOKUP(A29,Devengos!$A$4:$I$389,9,0) -> 5628456 | AG29: =IF(D29="Integral",ROUND(AF29*70%,0),AF29) -> 5628456 | AH29: =IFERROR(VLOOKUP(B29,'Planilla Mes anterior'!$CX:$CY,2,0),0) -> 5628456 | AJ29: 0
A30: 20087555 | B30: 13928419 | C30: JAUREGUI PACHECO DUBIAN YAMID | D30: Normal | E30: 30 | F30: 0 | G30: 2 | H30: 8818009 | I30: 8818009 | J30: 788500 | K30: 9606509 | L30: 3842604 | P30: 8818010 | Q30: 0 | R30: 0 | T30: 0 | V30: 352720 | Y30: 352720 | AC30: 88200 | AF30: =VLOOKUP(A30,Devengos!$A$4:$I$389,9,0) -> 8818010 | AG30: =IF(D30="Integral",ROUND(AF30*70%,0),AF30) -> 8818010 | AH30: =IFERROR(VLOOKUP(B30,'Planilla Mes anterior'!$CX:$CY,2,0),0) -> 8818010 | AJ30: 0
A31: 20088951 | B31: 743339 | C31: AULAR CASTELLANOS LISETTE KATHERINE | D31: Normal | E31: 30 | F31: 0 | G31: 0 | H31: 9703467 | I31: 9703467 | J31: 797500 | K31: 10500967 | L31: 4200387 | P31: 9703467 | Q31: 0 | R31: 0 | T31: 0 | V31: 388139 | Y31: 388139 | AC31: 97200 | AF31: =VLOOKUP(A31,Devengos!$A$4:$I$389,9,0) -> 9703467 | AG31: =IF(D31="Integral",ROUND(AF31*70%,0),AF31) -> 9703467 | AH31: =IFERROR(VLOOKUP(B31,'Planilla Mes anterior'!$CX:$CY,2,0),0) -> 9703467 | AJ31: 0
A32: 20090398 | B32: 1143831936 | C32: ZURITA RAMOS JEISON ANDRES | D32: Normal | E32: 30 | F32: 0 | G32: 0 | H32: 7378396 | I32: 7378396 | J32: 774100 | K32: 8152496 | L32: 3260998 | P32: 7378396 | Q32: 0 | R32: 0 | T32: 0 | V32: 295136 | Y32: 295136 | AC32: 73800 | AF32: =VLOOKUP(A32,Devengos!$A$4:$I$389,9,0) -> 7378396 | AG32: =IF(D32="Integral",ROUND(AF32*70%,0),AF32) -> 7378396 | AH32: =IFERROR(VLOOKUP(B32,'Planilla Mes anterior'!$CX:$CY,2,0),0) -> 7378396 | AJ32: 0
A33: 20090881 | B33: 79957003 | C33: MORENO TORRES JUAN PABLO | D33: Normal | E33: 30 | F33: 0 | G33: 0 | H33: 9870390 | I33: 9870390 | J33: 1468736 | K33: 11339126 | L33: 4535650 | P33: 9870390 | Q33: 0 | R33: 0 | T33: 0 | V33: 394816 | Y33: 394816 | AC33: 98800 | AF33: =VLOOKUP(A33,Devengos!$A$4:$I$389,9,0) -> 9870390 | AG33: =IF(D33="Integral",ROUND(AF33*70%,0),AF33) -> 9870390 | AH33: =IFERROR(VLOOKUP(B33,'Planilla Mes anterior'!$CX:$CY,2,0),0) -> 9870390 | AJ33: 0
A34: 20091394 | B34: 1.0537795e+09 | C34: EPALZA GONZALEZ JHON ALEJANDRO | D34: Integral | E34: 31 | F34: 10 | G34: 0 | H34: 19800886 | I34: 13860620 | J34: 897900 | K34: 20698786 | L34: 8279514 | P34: 17552468 | Q34: 5850823 | R34: 0 | V34: 788457 | Y34: 788457 | AC34: 197600 | AF34: =VLOOKUP(A34,Devengos!$A$4:$I$389,9,0) -> 22761766 | AG34: =IF(D34="Integral",ROUND(AF34*70%,0),AF34) -> 15933236 | AH34: =IFERROR(VLOOKUP(B34,'Planilla Mes anterior'!$CX:$CY,2,0),0) -> 17552468 | AJ34: 0
A35: 20092674 | B35: 52910485 | C35: RINCON GARZON DIANA YOMARA | D35: Normal | E35: 30 | F35: 0 | G35: 0 | H35: 6864198 | I35: 6864198 | J35: 700300 | K35: 7564498 | L35: 3025799 | P35: 6864198 | Q35: 0 | R35: 0 | T35: 0 | V35: 274568 | Y35: 274568 | AC35: 0 | AF35: =VLOOKUP(A35,Devengos!$A$4:$I$389,9,0) -> 6864198 | AG35: =IF(D35="Integral",ROUND(AF35*70%,0),AF35) -> 6864198 | AH35: =IFERROR(VLOOKUP(B35,'Planilla Mes anterior'!$CX:$CY,2,0),0) -> 6864198 | AJ35: 0
A36: 20095697 | B36: 52704384 | C36: CAVIEDES LUNA GYSELLA | D36: Normal | E36: 31 | F36: 0 | G36: 0 | H36: 4707860 | I36: 4707860 | J36: 760609 | K36: 5468469 | L36: 2187388 | P36: 3713188 | Q36: 0 | R36: 0 | T36: 0 | V36: 188314 | Y36: 188314 | AC36: 0 | AF36: =VLOOKUP(A36,Devengos!$A$4:$I$389,9,0) -> 3713187.9 | AG36: =IF(D36="Integral",ROUND(AF36*70%,0),AF36) -> 3713187.9 | AH36: =IFERROR(VLOOKUP(B36,'Planilla Mes anterior'!$CX:$CY,2,0),0) -> 3713188 | AJ36: 0
A37: 20096418 | B37: 80093596 | C37: CANTOR CORTES HECTOR MAURICIO | D37: Integral | E37: 30 | F37: 1 | G37: 0 | H37: 26798161 | I37: 18758713 | J37: 1439924 | K37: 28238085 | L37: 11295234 | P37: 19405565 | Q37: 646852 | R37: 0 | V37: 776223 | Y37: 776223 | AC37: 194200 | AF37: =VLOOKUP(A37,Devengos!$A$4:$I$389,9,0) -> 27722235 | AG37: =IF(D37="Integral",ROUND(AF37*70%,0),AF37) -> 19405565 | AH37: =IFERROR(VLOOKUP(B37,'Planilla Mes anterior'!$CX:$CY,2,0),0) -> 19405565 | AJ37: 0
A38: 20097480 | B38: 29659821 | C38: BENAVIDES URIBE ISABEL CRISTINA | D38: Normal | E38: 31 | F38: 0 | G38: 0 | H38: 13337351 | I38: 13337351 | J38: 833700 | K38: 14171051 | L38: 5668420 | P38: 16092832 | Q38: 0 | R38: 0 | T38: 0 | V38: 533494 | Y38: 533494 | AC38: 133400 | AF38: =VLOOKUP(A38,Devengos!$A$4:$I$389,9,0) -> 12245239 | AG38: =IF(D38="Integral",ROUND(AF38*70%,0),AF38) -> 12245239 | AH38: =IFERROR(VLOOKUP(B38,'Planilla Mes anterior'!$CX:$CY,2,0),0) -> 16092832 | AJ38: 0
A39: 20097763 | B39: 80124057 | C39: ARAQUE GUERRERO JAIME ALEJANDRO | D39: Normal | E39: 31 | F39: 0 | G39: 0 | H39: 15632953 | I39: 15632953 | J39: 856700 | K39: 16489653 | L39: 6595861 | P39: 14884659 | Q39: 0 | R39: 0 | T39: 0 | V39: 625318 | Y39: 625318 | AC39: 156400 | AF39: =VLOOKUP(A39,Devengos!$A$4:$I$389,9,0) -> 12639772 | AG39: =IF(D39="Integral",ROUND(AF39*70%,0),AF39) -> 12639772 | AH39: =IFERROR(VLOOKUP(B39,'Planilla Mes anterior'!$CX:$CY,2,0),0) -> 14884659 | AJ39: 0
A40: 20098732 | B40: 53010880 | C40: BULLA LOPEZ CLAUDIA MARCELA | D40: Normal | E40: 30 | F40: 0 | G40: 0 | H40: 9483131 | I40: 9483131 | J40: 795300 | K40: 10278431 | L40: 4111372 | P40: 9595056 | Q40: 0 | R40: 0 | T40: 0 | V40: 379325 | Y40: 379325 | AC40: 95000 | AF40: =VLOOKUP(A40,Devengos!$A$4:$I$389,9,0) -> 9483131 | AG40: =IF(D40="Integral",ROUND(AF40*70%,0),AF40) -> 9483131 | AH40: =IFERROR(VLOOKUP(B40,'Planilla Mes anterior'!$CX:$CY,2,0),0) -> 9595056 | AJ40: 0
A41: 20099217 | B41: 1.0709662e+09 | C41: MESA RODRIGUEZ JUAN DIEGO | D41: Normal | E41: 30 | F41: 0 | G41: 0 | H41: 8565526 | I41: 8565526 | J41: 786100 | K41: 9351626 | L41: 3740650 | P41: 8570675 | Q41: 0 | R41: 0 | T41: 0 | V41: 342621 | Y41: 342621 | AC41: 85800 | AF41: =VLOOKUP(A41,Devengos!$A$4:$I$389,9,0) -> 8565526 | AG41: =IF(D41="Integral",ROUND(AF41*70%,0),AF41) -> 8565526 | AH41: =IFERROR(VLOOKUP(B41,'Planilla Mes anterior'!$CX:$CY,2,0),0) -> 8570675 | AJ41: 0
A42: 20100638 | B42: 25291403 | C42: PORTILLA CONSTAIN NICOLE BEATRIZ | D42: Normal | E42: 30 | F42: 2 | G42: 0 | H42: 8359020 | I42: 8359020 | J42: 789900 | K42: 9148920 | L42: 3659568 | P42: 8956093 | Q42: 597073 | R42: 0 | T42: 0 | V42: 358244 | Y42: 358244 | AC42: 89600 | AF42: =VLOOKUP(A42,Devengos!$A$4:$I$389,9,0) -> 8956093 | AG42: =IF(D42="Integral",ROUND(AF42*70%,0),AF42) -> 8956093 | AH42: =IFERROR(VLOOKUP(B42,'Planilla Mes anterior'!$CX:$CY,2,0),0) -> 8956093 | AJ42: 0
A43: 20101530 | B43: 73576977 | C43: LEON RODRIGUEZ GEBERT | D43: Normal | E43: 30 | F43: 0 | G43: 0 | H43: 7301885 | I43: 7301885 | J43: 773500 | K43: 8075385 | L43: 3230154 | P43: 7301885 | Q43: 0 | R43: 0 | T43: 0 | V43: 292075 | Y43: 292075 | AC43: 73200 | AF43: =VLOOKUP(A43,Devengos!$A$4:$I$389,9,0) -> 7301885 | AG43: =IF(D43="Integral",ROUND(AF43*70%,0),AF43) -> 7301885 | AH43: =IFERROR(VLOOKUP(B43,'Planilla Mes anterior'!$CX:$CY,2,0),0) -> 7301885 | AJ43: 0
A44: 20102544 | B44: 1057575242 | C44: LADINO VEGA JHOLBERT GEOVANNY | D44: Normal | E44: 30 | F44: 0 | G44: 0 | H44: 7670699 | I44: 7670699 | J44: 777100 | K44: 8447799 | L44: 3379120 | P44: 7670699 | Q44: 0 | R44: 0 | T44: 0 | V44: 306828 | Y44: 306828 | AC44: 76800 | AF44: =VLOOKUP(A44,Devengos!$A$4:$I$389,9,0) -> 7670699 | AG44: =IF(D44="Integral",ROUND(AF44*70%,0),AF44) -> 7670699 | AH44: =IFERROR(VLOOKUP(B44,'Planilla Mes anterior'!$CX:$CY,2,0),0) -> 7670699 | AJ44: 0
A45: 20104631 | B45: 1127044383 | C45: LEON ASENSIO JONATHAN | D45: Normal | E45: 30 | F45: 0 | G45: 0 | H45: 10270325 | I45: 10270325 | J45: 803100 | K45: 11073425 | L45: 4429370 | P45: 9147658 | Q45: 0 | R45: 0 | T45: 0 | V45: 410813 | Y45: 410813 | AC45: 102800 | AF45: =VLOOKUP(A45,Devengos!$A$4:$I$389,9,0) -> 9147658 | AG45: =IF(D45="Integral",ROUND(AF45*70%,0),AF45) -> 9147658 | AH45: =IFERROR(VLOOKUP(B45,'Planilla Mes anterior'!$CX:$CY,2,0),0) -> 9147658 | AJ45: 0
A46: 20105895 | B46: 1046195 | C46: BESTEIRO OCHOA JESUS RAFAEL | D46: Normal | E46: 30 | F46: 0 | G46: 0 | H46: 14893496 | I46: 14893496 | J46: 1014278 | K46: 15907774 | L46: 6363110 | P46: 24134297 | Q46: 0 | R46: 0 | T46: 0 | V46: 595740 | Y46: 595740 | AC46: 149000 | AF46: =VLOOKUP(A46,Devengos!$A$4:$I$389,9,0) -> 12529900 | AG46: =IF(D46="Integral",ROUND(AF46*70%,0),AF46) -> 12529900 | AH46: =IFERROR(VLOOKUP(B46,'Planilla Mes anterior'!$CX:$CY,2,0),0) -> 24134297 | AJ46: 0
A47: 20105947 | B47: 1.0323881e+09 | C47: VARGAS GUTIERREZ JUAN DANIEL | D47: Normal | E47: 30 | F47: 16 | G47: 0 | H47: 3659004 | I47: 3659004 | J47: 788100 | K47: 4447104 | L47: 1778842 | P47: 9488488 | Q47: 5060527 | R47: 0 | T47: 0 | V47: 348782 | Y47: 348782 | AC47: 87800 | AF47: =VLOOKUP(A47,Devengos!$A$4:$I$389,9,0) -> 7840722 | AG47: =IF(D47="Integral",ROUND(AF47*70%,0),AF47) -> 7840722 | AH47: =IFERROR(VLOOKUP(B47,'Planilla Mes anterior'!$CX:$CY,2,0),0) -> 9488488 | AJ47: 0
A48: 20106287 | B48: 2.0000259e+09 | C48: CARDONA PEREZ CARLOS ENRIQUE | D48: Integral | E48: 30 | F48: 2 | G48: 0 | H48: 21244314 | I48: 14871020 | J48: 859900 | K48: 22104214 | L48: 8841686 | P48: 15933236 | Q48: 1062216 | R48: 0 | V48: 637330 | Y48: 637330 | AC48: 159600 | AF48: =VLOOKUP(A48,Devengos!$A$4:$I$389,9,0) -> 22761765 | AG48: =IF(D48="Integral",ROUND(AF48*70%,0),AF48) -> 15933236 | AH48: =IFERROR(VLOOKUP(B48,'Planilla Mes anterior'!$CX:$CY,2,0),0) -> 15933236 | AJ48: 0
A49: 20106320 | B49: 42112562 | C49: ARIAS MEDINA YAMILE | D49: Normal | E49: 31 | F49: 0 | G49: 0 | H49: 14589942 | I49: 14589942 | J49: 846300 | K49: 15436242 | L49: 6174497 | P49: 8652404 | Q49: 0 | R49: 0 | T49: 0 | V49: 583598 | Y49: 583598 | AC49: 146000 | AF49: =VLOOKUP(A49,Devengos!$A$4:$I$389,9,0) -> 8652403.5 | AG49: =IF(D49="Integral",ROUND(AF49*70%,0),AF49) -> 8652403.5 | AH49: =IFERROR(VLOOKUP(B49,'Planilla Mes anterior'!$CX:$CY,2,0),0) -> 8652404 | AJ49: 0
A50: 20106429 | B50: 1069014 | C50: PAZ PETIT DAVID ENRIQUE | D50: Normal | E50: 30 | F50: 0 | G50: 0 | H50: 11850943 | I50: 11850943 | J50: 818900 | K50: 12669843 | L50: 5067937 | P50: 11850943 | Q50: 0 | R50: 0 | T50: 0 | V50: 474038 | Y50: 474038 | AC50: 118600 | AF50: =VLOOKUP(A50,Devengos!$A$4:$I$389,9,0) -> 11850943 | AG50: =IF(D50="Integral",ROUND(AF50*70%,0),AF50) -> 11850943 | AH50: =IFERROR(VLOOKUP(B50,'Planilla Mes anterior'!$CX:$CY,2,0),0) -> 11850943 | AJ50: 0
A51: 20106507 | B51: 1020417292 | C51: MAYA QUINTERO ANDRES | D51: Normal | E51: 32 | F51: 0 | G51: 0 | H51: 9399198 | I51: 9399198 | J51: 794300 | K51: 10193498 | L51: 4077399 | P51: 10091379 | Q51: 0 | R51: 0 | T51: 0 | V51: 375968 | Y51: 375968 | AC51: 94000 | AF51: =VLOOKUP(A51,Devengos!$A$4:$I$389,9,0) -> 7655832 | AG51: =IF(D51="Integral",ROUND(AF51*70%,0),AF51) -> 7655832 | AH51: =IFERROR(VLOOKUP(B51,'Planilla Mes anterior'!$CX:$CY,2,0),0) -> 10091379 | AJ51: 0
A52: 20106546 | B52: 1067535 | C52: DURAN JESUS EDUARDO | D52: Normal | E52: 30 | F52: 0 | G52: 0 | H52: 7876682 | I52: 7876682 | J52: 1107742 | K52: 8984424 | L52: 3593770 | P52: 7876682 | Q52: 0 | R52: 0 | T52: 0 | V52: 315067 | Y52: 315067 | AC52: 78800 | AF52: =VLOOKUP(A52,Devengos!$A$4:$I$389,9,0) -> 7876682 | AG52: =IF(D52="Integral",ROUND(AF52*70%,0),AF52) -> 7876682 | AH52: =IFERROR(VLOOKUP(B52,'Planilla Mes anterior'!$CX:$CY,2,0),0) -> 7876682 | AJ52: 0
A53: 20106931 | B53: 1055521 | C53: GUEVARA SEQUERA ROLANDO JOSE | D53: Integral | E53: 31 | F53: 0 | G53: 0 | H53: 37426387 | I53: 26198471 | J53: 962300 | K53: 38388687 | L53: 15355475 | P53: 15933237 | Q53: 0 | R53: 0 | V53: 1047939 | Y53: 1047939 | AC53: 262000 | AF53: =VLOOKUP(A53,Devengos!$A$4:$I$389,9,0) -> 22761766 | AG53: =IF(D53="Integral",ROUND(AF53*70%,0),AF53) -> 15933236 | AH53: =IFERROR(VLOOKUP(B53,'Planilla Mes anterior'!$CX:$CY,2,0),0) -> 15933237 | AJ53: 0
A54: 20107557 | B54: 39744202 | C54: VELASQUEZ RODRIGUEZ EDY ALEXY | D54: Normal | E54: 30 | F54: 0 | G54: 2 | H54: 8888958 | I54: 8888958 | J54: 789500 | K54: 9678458 | L54: 3871383 | P54: 8888960 | Q54: 0 | R54: 0 | T54: 0 | V54: 355558 | Y54: 355558 | AC54: 89200 | AF54: =VLOOKUP(A54,Devengos!$A$4:$I$389,9,0) -> 8888959 | AG54: =IF(D54="Integral",ROUND(AF54*70%,0),AF54) -> 8888959 | AH54: =IFERROR(VLOOKUP(B54,'Planilla Mes anterior'!$CX:$CY,2,0),0) -> 8888960 | AJ54: 0
A55: 20108116 | B55: 1018425238 | C55: PIEDRAHITA VELEZ CHRISTIAN EDUARDO | D55: Normal | E55: 31 | F55: 0 | G55: 0 | H55: 21712763 | I55: 21712763 | J55: 917500 | K55: 22630263 | L55: 9052105 | P55: 21712763 | Q55: 0 | R55: 0 | T55: 0 | V55: 868511 | Y55: 868511 | AC55: 217200 | AF55: =VLOOKUP(A55,Devengos!$A$4:$I$389,9,0) -> 15451031 | AG55: =IF(D55="Integral",ROUND(AF55*70%,0),AF55) -> 15451031 | AH55: =IFERROR(VLOOKUP(B55,'Planilla Mes anterior'!$CX:$CY,2,0),0) -> 21712763 | AJ55: 0
A56: 20108941 | B56: 71773168 | C56: CARRASQUILLA ARANGO JUAN DAVID | D56: Integral | E56: 30 | F56: 0 | G56: 0 | H56: 39386666 | I56: 27570666 | J56: 976100 | K56: 40362766 | L56: 16145106 | P56: 28934424 | Q56: 0 | R56: 0 | V56: 1102827 | Y56: 1102827 | AC56: 275800 | AF56: =VLOOKUP(A56,Devengos!$A$4:$I$389,9,0) -> 39386666 | AG56: =IF(D56="Integral",ROUND(AF56*70%,0),AF56) -> 27570666 | AH56: =IFERROR(VLOOKUP(B56,'Planilla Mes anterior'!$CX:$CY,2,0),0) -> 28934424 | AJ56: 0
A57: 20109084 | B57: 22468372 | C57: PAEZ SANJONELO BETTY PATRICIA | D57: Integral | E57: 30 | F57: 0 | G57: 0 | H57: 22960781 | I57: 16072547 | J57: 861100 | K57: 23821881 | L57: 9528752 | P57: 16072547 | Q57: 0 | R57: 0 | V57: 642902 | Y57: 642902 | AC57: 160800 | AF57: =VLOOKUP(A57,Devengos!$A$4:$I$389,9,0) -> 22960781 | AG57: =IF(D57="Integral",ROUND(AF57*70%,0),AF57) -> 16072547 | AH57: =IFERROR(VLOOKUP(B57,'Planilla Mes anterior'!$CX:$CY,2,0),0) -> 16072547 | AJ57: 0
A58: 20109086 | B58: 1098715380 | C58: CHACON ACEVEDO LAURA JULIANA | D58: Normal | E58: 30 | F58: 2 | G58: 0 | H58: 8143267 | I58: 8143267 | J58: 787900 | K58: 8931167 | L58: 3572467 | P58: 8724929 | Q58: 581662 | R58: 0 | T58: 0 | V58: 348997 | Y58: 348997 | AC58: 87600 | AF58: =VLOOKUP(A58,Devengos!$A$4:$I$389,9,0) -> 8724929 | AG58: =IF(D58="Integral",ROUND(AF58*70%,0),AF58) -> 8724929 | AH58: =IFERROR(VLOOKUP(B58,'Planilla Mes anterior'!$CX:$CY,2,0),0) -> 8724929 | AJ58: 0
A59: 20109373 | B59: 15445652 | C59: ALZATE ARCILA SAUL EFREN | D59: Integral | E59: 30 | F59: 2 | G59: 0 | H59: 21244314 | I59: 14871020 | J59: 861100 | K59: 22105414 | L59: 8842166 | P59: 17854885 | Q59: 1190326 | R59: 0 | V59: 642454 | Y59: 642454 | AC59: 160800 | AF59: =VLOOKUP(A59,Devengos!$A$4:$I$389,9,0) -> 22761765 | AG59: =IF(D59="Integral",ROUND(AF59*70%,0),AF59) -> 15933236 | AH59: =IFERROR(VLOOKUP(B59,'Planilla Mes anterior'!$CX:$CY,2,0),0) -> 17854885 | AJ59: 0 | AK59: TOMA SALARIO * 70%+ EL PAGO DEL 100% DE LA INCAPACIDAD INCLUIDO EL AUXILIO ASUMIDO
A60: 20109421 | B60: 71762344 | C60: MONSALVE VARGAS DAVID ALEJANDRO | D60: Integral | E60: 30 | F60: 0 | G60: 0 | H60: 22761765 | I60: 15933235 | J60: 859700 | K60: 23621465 | L60: 9448586 | P60: 15933236 | Q60: 0 | R60: 0 | V60: 637329 | Y60: 637329 | AC60: 159400 | AF60: =VLOOKUP(A60,Devengos!$A$4:$I$389,9,0) -> 22761765 | AG60: =IF(D60="Integral",ROUND(AF60*70%,0),AF60) -> 15933236 | AH60: =IFERROR(VLOOKUP(B60,'Planilla Mes anterior'!$CX:$CY,2,0),0) -> 15933236 | AJ60: 0
A61: 20109450 | B61: 79643778 | C61: TORRES TORRES JAIRO ENRIQUE | D61: Normal | E61: 30 | F61: 1 | G61: 0 | H61: 5703329 | I61: 5703329 | J61: 700300 | K61: 6403629 | L61: 2561452 | P61: 4177153 | Q61: 139238 | R61: 0 | T61: 0 | V61: 233703 | Y61: 233703 | AC61: 0 | AF61: =VLOOKUP(A61,Devengos!$A$4:$I$389,9,0) -> 4351084 | AG61: =IF(D61="Integral",ROUND(AF61*70%,0),AF61) -> 4351084 | AH61: =IFERROR(VLOOKUP(B61,'Planilla Mes anterior'!$CX:$CY,2,0),0) -> 4177153 | AJ61: 0
A62: 20109676 | B62: 1.0171646e+09 | C62: SILVA AGUDELO CARLOS ANDRES | D62: Integral | E62: 30 | F62: 0 | G62: 0 | H62: 22761765 | I62: 15933235 | J62: 1003066 | K62: 23764831 | L62: 9505932 | P62: 15933236 | Q62: 0 | R62: 0 | V62: 637329 | Y62: 637329 | AC62: 159400 | AF62: =VLOOKUP(A62,Devengos!$A$4:$I$389,9,0) -> 22761765 | AG62: =IF(D62="Integral",ROUND(AF62*70%,0),AF62) -> 15933236 | AH62: =IFERROR(VLOOKUP(B62,'Planilla Mes anterior'!$CX:$CY,2,0),0) -> 15933236 | AJ62: 0
A63: 20109708 | B63: 8031259 | C63: RUIZ FLOREZ RAFAEL ANTONIO | D63: Integral | E63: 30 | F63: 0 | G63: 0 | H63: 26758523 | I63: 18730966 | J63: 887700 | K63: 27646223 | L63: 11058489 | P63: 18730967 | Q63: 0 | R63: 0 | V63: 749239 | Y63: 749239 | AC63: 187400 | AF63: =VLOOKUP(A63,Devengos!$A$4:$I$389,9,0) -> 26758523 | AG63: =IF(D63="Integral",ROUND(AF63*70%,0),AF63) -> 18730966 | AH63: =IFERROR(VLOOKUP(B63,'Planilla Mes anterior'!$CX:$CY,2,0),0) -> 18730967 | AJ63: 0
A64: 20109859 | B64: 15372073 | C64: FLOREZ ACEVEDO JULIAN DAVID | D64: Integral | E64: 30 | F64: 0 | G64: 0 | H64: 22761765 | I64: 15933235 | J64: 859700 | K64: 23621465 | L64: 9448586 | P64: 15933236 | Q64: 0 | R64: 0 | V64: 637329 | Y64: 637329 | AC64: 159400 | AF64: =VLOOKUP(A64,Devengos!$A$4:$I$389,9,0) -> 22761765 | AG64: =IF(D64="Integral",ROUND(AF64*70%,0),AF64) -> 15933236 | AH64: =IFERROR(VLOOKUP(B64,'Planilla Mes anterior'!$CX:$CY,2,0),0) -> 15933236 | AJ64: 0
A65: 20110044 | B65: 1.0369488e+09 | C65: EUSSE ECHEVERRI SEBASTIAN | D65: Integral | E65: 30 | F65: 0 | G65: 0 | H65: 22761765 | I65: 15933235 | J65: 859700 | K65: 23621465 | L65: 9448586 | P65: 15933236 | Q65: 0 | R65: 0 | V65: 637329 | Y65: 637329 | AC65: 159400 | AF65: =VLOOKUP(A65,Devengos!$A$4:$I$389,9,0) -> 22761765 | AG65: =IF(D65="Integral",ROUND(AF65*70%,0),AF65) -> 15933236 | AH65: =IFERROR(VLOOKUP(B65,'Planilla Mes anterior'!$CX:$CY,2,0),0) -> 15933236 | AJ65: 0
A66: 20110072 | B66: 1039458034 | C66: CEBALLOS JIMENEZ KELLY NASYARY | D66: Normal | E66: 30 | F66: 1 | G66: 0 | H66: 12808333 | I66: 12808333 | J66: 833100 | K66: 13641433 | L66: 5456573 | P66: 13250000 | Q66: 441667 | R66: 0 | T66: 0 | V66: 530000 | Y66: 530000 | AC66: 132800 | AF66: =VLOOKUP(A66,Devengos!$A$4:$I$389,9,0) -> 13250000 | AG66: =IF(D66="Integral",ROUND(AF66*70%,0),AF66) -> 13250000 | AH66: =IFERROR(VLOOKUP(B66,'Planilla Mes anterior'!$CX:$CY,2,0),0) -> 13250000 | AJ66: 0
A67: 20110129 | B67: 98716603 | C67: VARGAS TUBERQUIA RAFAEL ESTEBAN | D67: Integral | E67: 30 | F67: 0 | G67: 0 | H67: 23146404 | I67: 16202483 | J67: 862500 | K67: 24008904 | L67: 9603562 | P67: 16202483 | Q67: 0 | R67: 0 | V67: 648099 | Y67: 648099 | AC67: 162200 | AF67: =VLOOKUP(A67,Devengos!$A$4:$I$389,9,0) -> 23146404 | AG67: =IF(D67="Integral",ROUND(AF67*70%,0),AF67) -> 16202483 | AH67: =IFERROR(VLOOKUP(B67,'Planilla Mes anterior'!$CX:$CY,2,0),0) -> 16202483 | AJ67: 0
A68: 20110275 | B68: 8356257 | C68: ARANGO PALACIO CESAR ALEJANDRO | D68: Integral | E68: 30 | F68: 0 | G68: 0 | H68: 26755114 | I68: 18728580 | J68: 887700 | K68: 27642814 | L68: 11057126 | P68: 19779906 | Q68: 0 | R68: 0 | V68: 749143 | Y68: 749143 | AC68: 187400 | AF68: =VLOOKUP(A68,Devengos!$A$4:$I$389,9,0) -> 26755114 | AG68: =IF(D68="Integral",ROUND(AF68*70%,0),AF68) -> 18728580 | AH68: =IFERROR(VLOOKUP(B68,'Planilla Mes anterior'!$CX:$CY,2,0),0) -> 19779906 | AJ68: 0
A69: 20110381 | B69: 1017214574 | C69: VASQUEZ HERNANDEZ PEDRO IVAN | D69: Normal | E69: 30 | F69: 3 | G69: 0 | H69: 10856306 | I69: 10856306 | J69: 821500 | K69: 11677806 | L69: 4671122 | P69: 12513075 | Q69: 1251308 | R69: 0 | T69: 0 | V69: 484304 | Y69: 484304 | AC69: 121200 | AF69: =VLOOKUP(A69,Devengos!$A$4:$I$389,9,0) -> 12062562 | AG69: =IF(D69="Integral",ROUND(AF69*70%,0),AF69) -> 12062562 | AH69: =IFERROR(VLOOKUP(B69,'Planilla Mes anterior'!$CX:$CY,2,0),0) -> 12513075 | AJ69: 0
A70: 20110390 | B70: 43921183 | C70: JARAMILLO BERMUDEZ SANDRA MILENA | D70: Integral | E70: 35 | F70: 1 | G70: 3 | H70: 22003898 | I70: 15402729 | J70: 859900 | K70: 22863798 | L70: 9145519 | P70: 15938385 | Q70: 531280 | R70: 0 | V70: 637371 | Y70: 637371 | AC70: 159600 | AF70: =VLOOKUP(A70,Devengos!$A$4:$I$389,9,0) -> 22761765 | AG70: =IF(D70="Integral",ROUND(AF70*70%,0),AF70) -> 15933236 | AH70: =IFERROR(VLOOKUP(B70,'Planilla Mes anterior'!$CX:$CY,2,0),0) -> 15938385 | AJ70: 0
A71: 20110606 | B71: 1152440465 | C71: HINCAPIE ARIAS JUAN MANUEL | D71: Normal | E71: 30 | F71: 0 | G71: 0 | H71: 13477877 | I71: 13477877 | J71: 835100 | K71: 14312977 | L71: 5725191 | P71: 13477877 | Q71: 0 | R71: 0 | T71: 0 | V71: 539115 | Y71: 539115 | AC71: 134800 | AF71: =VLOOKUP(A71,Devengos!$A$4:$I$389,9,0) -> 13477877 | AG71: =IF(D71="Integral",ROUND(AF71*70%,0),AF71) -> 13477877 | AH71: =IFERROR(VLOOKUP(B71,'Planilla Mes anterior'!$CX:$CY,2,0),0) -> 13477877 | AJ71: 0
A72: 20110625 | B72: 1152456985 | C72: MORENO RINCON MARIO JAVIER | D72: Normal | E72: 30 | F72: 0 | G72: 0 | H72: 10590228 | I72: 10590228 | J72: 806300 | K72: 11396528 | L72: 4558611 | P72: 10590228 | Q72: 0 | R72: 0 | T72: 0 | V72: 423609 | Y72: 423609 | AC72: 106000 | AF72: =VLOOKUP(A72,Devengos!$A$4:$I$389,9,0) -> 10590228 | AG72: =IF(D72="Integral",ROUND(AF72*70%,0),AF72) -> 10590228 | AH72: =IFERROR(VLOOKUP(B72,'Planilla Mes anterior'!$CX:$CY,2,0),0) -> 10590228 | AJ72: 0
A73: 20110627 | B73: 1152438320 | C73: ECHAVARRIA RESTREPO MARIA | D73: Integral | E73: 30 | F73: 0 | G73: 0 | H73: 22761765 | I73: 15933235 | J73: 1462788 | K73: 24224553 | L73: 9689821 | P73: 15933236 | Q73: 0 | R73: 0 | V73: 637329 | Y73: 637329 | AC73: 159400 | AF73: =VLOOKUP(A73,Devengos!$A$4:$I$389,9,0) -> 22761765 | AG73: =IF(D73="Integral",ROUND(AF73*70%,0),AF73) -> 15933236 | AH73: =IFERROR(VLOOKUP(B73,'Planilla Mes anterior'!$CX:$CY,2,0),0) -> 15933236 | AJ73: 0
A74: 20110681 | B74: 9731158 | C74: JIMENEZ JARAMILLO ALVARO | D74: Integral | E74: 30 | F74: 0 | G74: 0 | H74: 22761765 | I74: 15933235 | J74: 859700 | K74: 23621465 | L74: 9448586 | P74: 15933236 | Q74: 0 | R74: 0 | V74: 637329 | Y74: 637329 | AC74: 159400 | AF74: =VLOOKUP(A74,Devengos!$A$4:$I$389,9,0) -> 22761765 | AG74: =IF(D74="Integral",ROUND(AF74*70%,0),AF74) -> 15933236 | AH74: =IFERROR(VLOOKUP(B74,'Planilla Mes anterior'!$CX:$CY,2,0),0) -> 15933236 | AJ74: 0
A75: 20110772 | B75: 1144150245 | C75: GONZALEZ MUNOZ YERMINSON DONEY | D75: Normal | E75: 35 | F75: 2 | G75: 0 | H75: 14067806 | I75: 14067806 | J75: 851100 | K75: 14918906 | L75: 5967562 | P75: 14725350 | Q75: 981690 | R75: 0 | T75: 0 | V75: 601980 | Y75: 601980 | AC75: 150800 | AF75: =VLOOKUP(A75,Devengos!$A$4:$I$389,9,0) -> 14485350 | AG75: =IF(D75="Integral",ROUND(AF75*70%,0),AF75) -> 14485350 | AH75: =IFERROR(VLOOKUP(B75,'Planilla Mes anterior'!$CX:$CY,2,0),0) -> 14725350 | AJ75: 0
A76: 20111034 | B76: 498932 | C76: TUA DIAZ ESPERANZA DE JESUS | D76: Integral | E76: 30 | F76: 0 | G76: 0 | H76: 22761765 | I76: 15933235 | J76: 859700 | K76: 23621465 | L76: 9448586 | P76: 22761766 | Q76: 0 | R76: 0 | V76: 637329 | Y76: 637329 | AC76: 159400 | AF76: =VLOOKUP(A76,Devengos!$A$4:$I$389,9,0) -> 22761765 | AG76: =IF(D76="Integral",ROUND(AF76*70%,0),AF76) -> 15933236 | AH76: =IFERROR(VLOOKUP(B76,'Planilla Mes anterior'!$CX:$CY,2,0),0) -> 15933236 | AJ76: 0
A77: 20111088 | B77: 1098649460 | C77: MEJIA BASTIDAS CARLOS ANDRES | D77: Integral | E77: 30 | F77: 0 | G77: 0 | H77: 22761765 | I77: 15933235 | J77: 859700 | K77: 23621465 | L77: 9448586 | P77: 15933238 | Q77: 0 | R77: 0 | V77: 637329 | Y77: 637329 | AC77: 159400 | AF77: =VLOOKUP(A77,Devengos!$A$4:$I$389,9,0) -> 22761765 | AG77: =IF(D77="Integral",ROUND(AF77*70%,0),AF77) -> 15933236 | AH77: =IFERROR(VLOOKUP(B77,'Planilla Mes anterior'!$CX:$CY,2,0),0) -> 15933238 | AJ77: 0
A78: 20111115 | B78: 1.040743e+09 | C78: ROZO HOYOS LAURA CAROLINA | D78: Normal | E78: 30 | F78: 0 | G78: 2 | H78: 9406000 | I78: 9406000 | J78: 794500 | K78: 10200500 | L78: 4080200 | P78: 9406000 | Q78: 0 | R78: 0 | T78: 0 | V78: 376240 | Y78: 376240 | AC78: 94200 | AF78: =VLOOKUP(A78,Devengos!$A$4:$I$389,9,0) -> 9406000 | AG78: =IF(D78="Integral",ROUND(AF78*70%,0),AF78) -> 9406000 | AH78: =IFERROR(VLOOKUP(B78,'Planilla Mes anterior'!$CX:$CY,2,0),0) -> 9406000 | AJ78: 0
A79: 20111496 | B79: 1075231064 | C79: BOTERO SALAZAR CAMILO HERNANDO | D79: Integral | E79: 31 | F79: 0 | G79: 0 | H79: 29924537 | I79: 20947176 | J79: 909900 | K79: 30834437 | L79: 12333775 | P79: 20251187 | Q79: 0 | R79: 0 | V79: 837887 | Y79: 837887 | AC79: 209600 | AF79: =VLOOKUP(A79,Devengos!$A$4:$I$389,9,0) -> 22761766 | AG79: =IF(D79="Integral",ROUND(AF79*70%,0),AF79) -> 15933236 | AH79: =IFERROR(VLOOKUP(B79,'Planilla Mes anterior'!$CX:$CY,2,0),0) -> 20251187 | AJ79: 0
A80: 20111576 | B80: 72292772 | C80: LOPEZ PALACIO JUAN SEBASTIAN | D80: Normal | E80: 30 | F80: 0 | G80: 0 | H80: 7728466 | I80: 7728466 | J80: 777700 | K80: 8506166 | L80: 3402466 | P80: 7077467 | Q80: 0 | R80: 0 | T80: 0 | V80: 309139 | Y80: 309139 | AC80: 77400 | AF80: =VLOOKUP(A80,Devengos!$A$4:$I$389,9,0) -> 6986327 | AG80: =IF(D80="Integral",ROUND(AF80*70%,0),AF80) -> 6986327 | AH80: =IFERROR(VLOOKUP(B80,'Planilla Mes anterior'!$CX:$CY,2,0),0) -> 7077467 | AJ80: 0
A81: 80113191 | B81: 1019005630 | C81: MORENO SANCHEZ DAVID CAMILO | D81: Normal | E81: 16 | F81: 0 | G81: 0 | H81: 3258228 | I81: 3258228 | J81: 373494 | K81: 3631722 | L81: 1452689 | P81: 6109178 | Q81: 0 | R81: 0 | T81: 0 | V81: 130329 | Y81: 130329 | AC81: 0 | AF81: =VLOOKUP(A81,Devengos!$A$4:$I$389,9,0) -> 6109178 | AG81: =IF(D81="Integral",ROUND(AF81*70%,0),AF81) -> 6109178 | AH81: =IFERROR(VLOOKUP(B81,'Planilla Mes anterior'!$CX:$CY,2,0),0) -> 6109178 | AJ81: 0
A82: 80113261 | B82: 1090485771 | C82: CACERES GRANADOS NICOLÁS EDUARDO | D82: Normal | E82: 30 | F82: 4 | G82: 0 | H82: 3949408 | I82: 3949408 | J82: 700300 | K82: 4649708 | L82: 1859883 | P82: 4557009 | Q82: 607601 | R82: 0 | T82: 0 | V82: 182280 | Y82: 182280 | AC82: 0 | AF82: =VLOOKUP(A82,Devengos!$A$4:$I$389,9,0) -> 4557009 | AG82: =IF(D82="Integral",ROUND(AF82*70%,0),AF82) -> 4557009 | AH82: =IFERROR(VLOOKUP(B82,'Planilla Mes anterior'!$CX:$CY,2,0),0) -> 4557009 | AJ82: 0
A83: 80113669 | B83: 1130622393 | C83: ILLERA BERMUDEZ ANTHONY | D83: Normal | E83: 30 | F83: 0 | G83: 0 | H83: 7510913 | I83: 7510913 | J83: 775500 | K83: 8286413 | L83: 3314565 | P83: 7510913 | Q83: 0 | R83: 0 | T83: 0 | V83: 300437 | Y83: 300437 | AC83: 75200 | AF83: =VLOOKUP(A83,Devengos!$A$4:$I$389,9,0) -> 7510913 | AG83: =IF(D83="Integral",ROUND(AF83*70%,0),AF83) -> 7510913 | AH83: =IFERROR(VLOOKUP(B83,'Planilla Mes anterior'!$CX:$CY,2,0),0) -> 7510913 | AJ83: 0
A84: 80115338 | B84: 1024492090 | C84: IZQUIERDO MORENO CRISTIAN ALFONSO | D84: Normal | E84: 30 | F84: 0 | G84: 0 | H84: 9016307 | I84: 9016307 | J84: 790500 | K84: 9806807 | L84: 3922723 | P84: 9016307 | Q84: 0 | R84: 0 | T84: 0 | V84: 360652 | Y84: 360652 | AC84: 90200 | AF84: =VLOOKUP(A84,Devengos!$A$4:$I$389,9,0) -> 9016307 | AG84: =IF(D84="Integral",ROUND(AF84*70%,0),AF84) -> 9016307 | AH84: =IFERROR(VLOOKUP(B84,'Planilla Mes anterior'!$CX:$CY,2,0),0) -> 9016307 | AJ84: 0
A85: 80115424 | B85: 24346479 | C85: ESPINEL ZULUAGA SANDRA MILENA | D85: Normal | E85: 30 | F85: 0 | G85: 0 | H85: 6256392 | I85: 6256392 | J85: 700300 | K85: 6956692 | L85: 2782677 | P85: 6256392 | Q85: 0 | R85: 0 | T85: 0 | V85: 250256 | Y85: 250256 | AC85: 0 | AF85: =VLOOKUP(A85,Devengos!$A$4:$I$389,9,0) -> 6256392 | AG85: =IF(D85="Integral",ROUND(AF85*70%,0),AF85) -> 6256392 | AH85: =IFERROR(VLOOKUP(B85,'Planilla Mes anterior'!$CX:$CY,2,0),0) -> 6256392 | AJ85: 0
A86: 80116018 | B86: 1.013608e+09 | C86: MARTINEZ MOGOLLON ADRIANA MARCELA | D86: Normal | E86: 30 | F86: 0 | G86: 0 | H86: 5469840 | I86: 5469840 | J86: 700300 | K86: 6170140 | L86: 2468056 | P86: 5469840 | Q86: 0 | R86: 0 | T86: 0 | V86: 218794 | Y86: 218794 | AC86: 0 | AF86: =VLOOKUP(A86,Devengos!$A$4:$I$389,9,0) -> 5469840 | AG86: =IF(D86="Integral",ROUND(AF86*70%,0),AF86) -> 5469840 | AH86: =IFERROR(VLOOKUP(B86,'Planilla Mes anterior'!$CX:$CY,2,0),0) -> 5469840 | AJ86: 0
A87: 80116712 | B87: 1037592678 | C87: MOLINA ESTRADA ALEJANDRO | D87: Normal | E87: 30 | F87: 3 | G87: 0 | H87: 4297152 | I87: 4297152 | J87: 700300 | K87: 4997452 | L87: 1998981 | P87: 4774614 | Q87: 477461 | R87: 0 | T87: 0 | V87: 190984 | Y87: 190984 | AC87: 0 | AF87: =VLOOKUP(A87,Devengos!$A$4:$I$389,9,0) -> 4774613 | AG87: =IF(D87="Integral",ROUND(AF87*70%,0),AF87) -> 4774613 | AH87: =IFERROR(VLOOKUP(B87,'Planilla Mes anterior'!$CX:$CY,2,0),0) -> 4774614 | AJ87: 0
A88: 80116856 | B88: 1098694653 | C88: MEZA MEZA GINA PAOLA | D88: Normal | E88: 30 | F88: 0 | G88: 0 | H88: 5559766 | I88: 5559766 | J88: 727249 | K88: 6287015 | L88: 2514806 | P88: 5559766 | Q88: 0 | R88: 0 | T88: 0 | V88: 222391 | Y88: 222391 | AC88: 0 | AF88: =VLOOKUP(A88,Devengos!$A$4:$I$389,9,0) -> 5559766 | AG88: =IF(D88="Integral",ROUND(AF88*70%,0),AF88) -> 5559766 | AH88: =IFERROR(VLOOKUP(B88,'Planilla Mes anterior'!$CX:$CY,2,0),0) -> 5559766 | AJ88: 0
A89: 80118328 | B89: 1.0136008e+09 | C89: GARCIA ALFONSO LETTY YISEL | D89: Normal | E89: 30 | F89: 0 | G89: 0 | H89: 4000000 | I89: 4000000 | J89: 525200 | K89: 4525200 | L89: 1810080 | P89: 3225001 | Q89: 0 | R89: 0 | T89: 0 | V89: 160000 | Y89: 160000 | AC89: 0 | AF89: =VLOOKUP(A89,Devengos!$A$4:$I$389,9,0) -> 4000000 | AG89: =IF(D89="Integral",ROUND(AF89*70%,0),AF89) -> 4000000 | AH89: =IFERROR(VLOOKUP(B89,'Planilla Mes anterior'!$CX:$CY,2,0),0) -> 3225001 | AJ89: 0
A90: 80118771 | B90: 1030669458 | C90: GORDILLO MARTINEZ DANIEL SANTIAGO | D90: Normal | E90: 30 | F90: 2 | G90: 0 | H90: 4061935 | I90: 4061935 | J90: 700300 | K90: 4762235 | L90: 1904894 | P90: 4352073 | Q90: 290138 | R90: 0 | T90: 0 | V90: 174083 | Y90: 174083 | AC90: 0 | AF90: =VLOOKUP(A90,Devengos!$A$4:$I$389,9,0) -> 4352073 | AG90: =IF(D90="Integral",ROUND(AF90*70%,0),AF90) -> 4352073 | AH90: =IFERROR(VLOOKUP(B90,'Planilla Mes anterior'!$CX:$CY,2,0),0) -> 4352073 | AJ90: 0
A91: 80119392 | B91: 1096190137 | C91: MCNISH FAJARDO CESAR IVAN | D91: Normal | E91: 30 | F91: 0 | G91: 0 | H91: 4199201 | I91: 4199201 | J91: 700300 | K91: 4899501 | L91: 1959800 | P91: 4199201 | Q91: 0 | R91: 0 | T91: 0 | V91: 167968 | Y91: 167968 | AC91: 0 | AF91: =VLOOKUP(A91,Devengos!$A$4:$I$389,9,0) -> 4199201 | AG91: =IF(D91="Integral",ROUND(AF91*70%,0),AF91) -> 4199201 | AH91: =IFERROR(VLOOKUP(B91,'Planilla Mes anterior'!$CX:$CY,2,0),0) -> 4199201 | AJ91: 0
... A97: 80123148 | B97: 1001067170 | C97: BAUTISTA WILCHES KEVIN ALEJANDRO | D97: Normal | E97: 30 | F97: 0 | G97: 0 | H97: 2307806 | I97: 2307806 | J97: 774200 | K97: 3082006 | L97: 1232802 | P97: 2307806 | Q97: 0 | R97: 0 | T97: 0 | V97: 92312 | Y97: 92312 | AC97: 0 | AF97: =VLOOKUP(A97,Devengos!$A$4:$I$389,9,0) -> 2307806 | AG97: =IF(D97="Integral",ROUND(AF97*70%,0),AF97) -> 2307806 | AH97: =IFERROR(VLOOKUP(B97,'Planilla Mes anterior'!$CX:$CY,2,0),0) -> 2307806 | AJ97: 0
A98: 80124088 | B98: 1151941692 | C98: PEREZ HERNANDEZ ANDRES MAURICIO | D98: Integral | E98: 30 | F98: 0 | G98: 0 | H98: 22761765 | I98: 15933235 | J98: 859700 | K98: 23621465 | L98: 9448586 | P98: 22761766 | Q98: 0 | R98: 0 | V98: 637329 | Y98: 637329 | AC98: 159400 | AF98: =VLOOKUP(A98,Devengos!$A$4:$I$389,9,0) -> 22761765 | AG98: =IF(D98="Integral",ROUND(AF98*70%,0),AF98) -> 15933236 | AH98: =IFERROR(VLOOKUP(B98,'Planilla Mes anterior'!$CX:$CY,2,0),0) -> 15933236 | AJ98: 0
A99: 80124137 | B99: 1.0381038e+09 | C99: SAAVEDRA RAMOS MARCOS AURELIO | D99: Normal | E99: 30 | F99: 0 | G99: 0 | H99: 2964368 | I99: 2964368 | J99: 774200 | K99: 3738568 | L99: 1495427 | P99: 2964368 | Q99: 0 | R99: 0 | T99: 0 | V99: 118575 | Y99: 118575 | AC99: 0 | AF99: =VLOOKUP(A99,Devengos!$A$4:$I$389,9,0) -> 2964368 | AG99: =IF(D99="Integral",ROUND(AF99*70%,0),AF99) -> 2964368 | AH99: =IFERROR(VLOOKUP(B99,'Planilla Mes anterior'!$CX:$CY,2,0),0) -> 2964368 | AJ99: 0
A100: 80125061 | B100: 80844918 | C100: SÁNCHEZ RUIZ ANDRÉS CAMILO | D100: Integral | E100: 30 | F100: 0 | G100: 0 | H100: 22761765 | I100: 15933235 | J100: 859700 | K100: 23621465 | L100: 9448586 | P100: 22761766 | Q100: 0 | R100: 0 | V100: 637329 | Y100: 637329 | AC100: 159400 | AF100: =VLOOKUP(A100,Devengos!$A$4:$I$389,9,0) -> 22761765 | AG100: =IF(D100="Integral",ROUND(AF100*70%,0),AF100) -> 15933236 | AH100: =IFERROR(VLOOKUP(B100,'Planilla Mes anterior'!$CX:$CY,2,0),0) -> 15933236 | AJ100: 0
A101: 80125201 | B101: 16944092 | C101: OCAMPO JARAMILLO OSCAR DANIEL | D101: Integral | E101: 30 | F101: 9 | G101: 0 | H101: 15933236 | I101: 11153265 | J101: 859900 | K101: 16793136 | L101: 6717254 | P101: 15933236 | Q101: 4779971 | R101: 0 | V101: 637330 | Y101: 637330 | AC101: 159600 | AF101: =VLOOKUP(A101,Devengos!$A$4:$I$389,9,0) -> 22761765 | AG101: =IF(D101="Integral",ROUND(AF101*70%,0),AF101) -> 15933236 | AH101: =IFERROR(VLOOKUP(B101,'Planilla Mes anterior'!$CX:$CY,2,0),0) -> 15933236 | AJ101: 0
A102: 80125328 | B102: 1.0366418e+09 | C102: DURANGO CIFUENTES MAYRA | D102: Normal | E102: 30 | F102: 0 | G102: 0 | H102: 17977500 | I102: 17977500 | J102: 880100 | K102: 18857600 | L102: 7543040 | P102: 17977500 | Q102: 0 | R102: 0 | T102: 0 | V102: 719100 | Y102: 719100 | AC102: 179800 | AF102: =VLOOKUP(A102,Devengos!$A$4:$I$389,9,0) -> 17977500 | AG102: =IF(D102="Integral",ROUND(AF102*70%,0),AF102) -> 17977500 | AH102: =IFERROR(VLOOKUP(B102,'Planilla Mes anterior'!$CX:$CY,2,0),0) -> 17977500 | AJ102: 0
A103: 80126016 | B103: 1140880066 | C103: SOLANO CARRILLO JESUS | D103: Normal | E103: 30 | F103: 0 | G103: 0 | H103: 12305000 | I103: 12305000 | J103: 823500 | K103: 13128500 | L103: 5251400 | P103: 12305000 | Q103: 0 | R103: 0 | T103: 0 | V103: 492200 | Y103: 492200 | AC103: 123200 | AF103: =VLOOKUP(A103,Devengos!$A$4:$I$389,9,0) -> 12305000 | AG103: =IF(D103="Integral",ROUND(AF103*70%,0),AF103) -> 12305000 | AH103: =IFERROR(VLOOKUP(B103,'Planilla Mes anterior'!$CX:$CY,2,0),0) -> 12305000 | AJ103: 0
A104: 80126210 | B104: 1.0369668e+09 | C104: SERNA BETANCUR SANTIAGO | D104: Normal | E104: 30 | F104: 0 | G104: 0 | H104: 2550000 | I104: 2550000 | J104: 525200 | K104: 3075200 | L104: 1230080 | P104: 2295000 | Q104: 0 | R104: 0 | T104: 0 | V104: 102000 | Y104: 102000 | AC104: 0 | AF104: =VLOOKUP(A104,Devengos!$A$4:$I$389,9,0) -> 2550000 | AG104: =IF(D104="Integral",ROUND(AF104*70%,0),AF104) -> 2550000 | AH104: =IFERROR(VLOOKUP(B104,'Planilla Mes anterior'!$CX:$CY,2,0),0) -> 2295000 | AJ104: 0
A105: 80126630 | B105: 1.0191484e+09 | C105: GOMEZ VELASQUEZ NICOLAS SANTIAGO | D105: Normal | E105: 30 | F105: 0 | G105: 0 | H105: 4000000 | I105: 4000000 | J105: 700300 | K105: 4700300 | L105: 1880120 | P105: 4327273 | Q105: 0 | R105: 0 | T105: 0 | V105: 160000 | Y105: 160000 | AC105: 0 | AF105: =VLOOKUP(A105,Devengos!$A$4:$I$389,9,0) -> 4000000 | AG105: =IF(D105="Integral",ROUND(AF105*70%,0),AF105) -> 4000000 | AH105: =IFERROR(VLOOKUP(B105,'Planilla Mes anterior'!$CX:$CY,2,0),0) -> 4327273 | AJ105: 0
...
